Workbook
Name Aporte: Planilha2!$D$22
Name Qnt_Anos: Planilha2!$D$23
Name Rendimento: Planilha2!$C$18
Name salario: Planilha2!$C$17
Name sugestao_investimento: Planilha2!$C$19
Name Taxa_Mensal: Planilha2!$D$24

Sheet Planilha1
B1: Criar um simulador de investimento
B2: Quanto investir por mês?
B3: Por quantos anos?
B4: Taxa de Rendimento Mensal?
B5: Qual PL total Acumulado?
B6: Qual Rendimento Mensal?
B13: Pefil | C13: Agressivo
B14: Valor a ser Investido por mês | C14: =Aporte -> 1500
B16: Tipo de FII | C16: % | D16: Valor
B17: Papel | C17: 0.2 | D17: =C17*Aporte -> 300
B18: Tijolo | C18: 0.5 | D18: =C18*Aporte -> 750
B19: Hibridos | C19: 0.05 | D19: =C19*Aporte -> 75
B20: Hedge Funds | C20: 0.25 | D20: =C20*Aporte -> 375
B21: Desenvolvimento | C21: 0 | D21: =C21*Aporte -> 0
A23: CHAVE | B23: PERFIL | C23: TIPO DE FII | D23: %
A24: =B24&"-"&C24 -> Conservador-Papel | B24: Conservador | C24: Papel | D24: 0.1
A25: =B25&"-"&C25 -> Conservador-Tijolo | B25: Conservador | C25: Tijolo | D25: 0.5
A26: =B26&"-"&C26 -> Conservador-Hibridos | B26: Conservador | C26: Hibridos | D26: 0.05
A27: =B27&"-"&C27 -> Conservador-Hedge Funds | B27: Conservador | C27: Hedge Funds | D27: 0.35 | H27: Moderado-Tijolo | I27: =VLOOKUP(H27,A24:D38,4) -> 0.2
A28: =B28&"-"&C28 -> Conservador-Desenvolvimento | B28: Conservador | C28: Desenvolvimento | D28: 0
A29: =B29&"-"&C29 -> Moderado-Papel | B29: Moderado | C29: Papel | D29: 0.1
A30: =B30&"-"&C30 -> Moderado-Tijolo | B30: Moderado | C30: Tijolo | D30: 0.2
A31: =B31&"-"&C31 -> Moderado-Hibridos | B31: Moderado | C31: Hibridos | D31: 0.1
A32: =B32&"-"&C32 -> Moderado-Hedge Funds | B32: Moderado | C32: Hedge Funds | D32: 0.5
A33: =B33&"-"&C33 -> Moderado-Desenvolvimento | B33: Moderado | C33: Desenvolvimento | D33: 0.1
A34: =B34&"-"&C34 -> Agressivo-Papel | B34: Agressivo | C34: Papel | D34: 0.2
A35: =B35&"-"&C35 -> Agressivo-Tijolo | B35: Agressivo | C35: Tijolo | D35: 0
A36: =B36&"-"&C36 -> Agressivo-Hibridos | B36: Agressivo | C36: Hibridos | D36: 0.1
A37: =B37&"-"&C37 -> Agressivo-Hedge Funds | B37: Agressivo | C37: Hedge Funds | D37: 0.5
A38: =B38&"-"&C38 -> Agressivo-Desenvolvimento | B38: Agressivo | C38: Desenvolvimento | D38: 0.2

Sheet Planilha2
B16: Configurações | F16: Pefil | G16: Conservador
B17: Salario | C17: 5000 | F17: Valor a ser Investido por mês | G17: =Aporte -> 1500
B18: Redimento Carteira | C18: 0.0099
B19: Sugestão de Investimento | C19: =C17*0.3 -> 1500 | F19: Tipo de FII | G19: % | H19: Valor
F20: Papel | G20: =VLOOKUP(($G$16&"-"&F20),Planilha1!$A$23:$D$38,4,FALSE) -> 0.1 | H20: =G20*Aporte -> 150
B21: Investimento mensal | F21: Tijolo | G21: =VLOOKUP(($G$16&"-"&F21),Planilha1!$A$23:$D$38,4,FALSE) -> 0.5 | H21: =G21*Aporte -> 750
B22: Quanto Investir por Mês? | D22: 1500 | F22: Hibridos | G22: =VLOOKUP(($G$16&"-"&F22),Planilha1!$A$23:$D$38,4,FALSE) -> 0.05 | H22: =G22*Aporte -> 75
B23: Por quantos anos? | D23: 5 | F23: Hedge Funds | G23: =VLOOKUP(($G$16&"-"&F23),Planilha1!$A$23:$D$38,4,FALSE) -> 0.35 | H23: =G23*Aporte -> 525
B24: Taxa de Rendimento Mensal? | D24: 0.0099 | F24: Desenvolvimento | G24: =VLOOKUP(($G$16&"-"&F24),Planilha1!$A$23:$D$38,4,FALSE) -> 0 | H24: =G24*Aporte -> 0
B25: PL Acumulado. | D25: =-FV(Taxa_Mensal,(Qnt_Anos*12),Aporte) -> 122111.5 | G25: =SUM(G20:G24) -> 1 | H25: =SUM(H20:H24) -> 1500
B26: Dividendo Mensal | D26: =D25*D24 -> 1208.9039
B28: Cenarios | E28: Dividendo
A29: 1 | B29: Quanto em 2 Anos? | D29: =-FV($D$24,($A29*12),$D$22) -> 19013.175 | E29: =D29*$C$18 -> 188.23044
A30: 5 | B30: Quanto em 5 Anos? | D30: =-FV($D$24,($A30*12),$D$22) -> 122111.5 | E30: =D30*$C$18 -> 1208.9039
A31: 10 | B31: Quanto em 10 Anos? | D31: =-FV($D$24,($A31*12),$D$22) -> 342637.04 | E31: =D31*$C$18 -> 3392.1067
A32: 20 | B32: Quanto em 20 Anos? | D32: =-FV($D$24,($A32*12),$D$22) -> 1460115 | E32: =D32*$C$18 -> 14455.139
A33: 30 | B33: Quanto em 30 Anos? | D33: =-FV($D$24,($A33*12),$D$22) -> 5104662.8 | E33: =D33*$C$18 -> 50536.161
